ingestar_vl_sdk/__init__.py
ingestar_vl_sdk/ingestar_client.py
ingestar_vl_sdk/structs.py
ingestar_vl_sdk/logits_processor/vllm_v0_no_repeat_ngram.py
ingestar_vl_sdk/logits_processor/vllm_v1_no_repeat_ngram.py
ingestar_vl_sdk/post_process/__init__.py
ingestar_vl_sdk/post_process/equation_big.py
ingestar_vl_sdk/post_process/equation_block.py
ingestar_vl_sdk/post_process/equation_double_subscript.py
ingestar_vl_sdk/post_process/equation_fix_eqqcolon.py
ingestar_vl_sdk/post_process/equation_left_right.py
ingestar_vl_sdk/post_process/equation_leq.py
ingestar_vl_sdk/post_process/otsl2html.py
ingestar_vl_sdk/vlm_client/__init__.py
ingestar_vl_sdk/vlm_client/base_client.py
ingestar_vl_sdk/vlm_client/http_client.py
ingestar_vl_sdk/vlm_client/transformers_client.py
ingestar_vl_sdk/vlm_client/utils.py
ingestar_vl_sdk/vlm_client/vllm_async_engine_client.py
ingestar_vl_sdk/vlm_client/vllm_engine_client.py
ingestar_vl_sdk-0.1.0.dist-info/licenses/LICENSE.md
ingestar_vl_sdk-0.1.0.dist-info/METADATA
ingestar_vl_sdk-0.1.0.dist-info/WHEEL
ingestar_vl_sdk-0.1.0.dist-info/top_level.txt
ingestar_vl_sdk-0.1.0.dist-info/RECORD
